{
  "date": "2026-06-12",
  "starting_value": 1051587.3215472035,
  "realized_pnl": -15358.192801461986,
  "ending_value_before_rebalance": 1036229.1287457414,
  "allocated_value": 1036229.1287457416,
  "cash_after_rebalance": -1.1641532182693481e-10,
  "exits": [
    {
      "ticker": "GOOGL",
      "side": "short",
      "entry_date": "2026-06-11",
      "entry_price": 355.92999267578125,
      "shares": 432.0561087973986,
      "notional": 153781.72763978463,
      "sentiment": -79.772223,
      "weight": 0.14623771558364276,
      "exit_date": "2026-06-12",
      "exit_price": 362.6199951171875,
      "pnl": -2890.4564226790812
    },
    {
      "ticker": "NVDA",
      "side": "short",
      "entry_date": "2026-06-11",
      "entry_price": 201.49000549316406,
      "shares": 525.4589179924626,
      "notional": 105874.72027273334,
      "sentiment": -54.921101,
      "weight": 0.10068086415967772,
      "exit_date": "2026-06-12",
      "exit_price": 204.86000061035156,
      "pnl": -1770.7939879172259
    },
    {
      "ticker": "MSFT",
      "side": "short",
      "entry_date": "2026-06-11",
      "entry_price": 395.2099914550781,
      "shares": 256.3887941841104,
      "notional": 101327.41315868005,
      "sentiment": -52.562245999999995,
      "weight": 0.09635663257103246,
      "exit_date": "2026-06-12",
      "exit_price": 391.42999267578125,
      "pnl": 969.149329041335
    },
    {
      "ticker": "AVGO",
      "side": "short",
      "entry_date": "2026-06-11",
      "entry_price": 372.82000732421875,
      "shares": 226.721023364262,
      "notional": 84526.13359121853,
      "sentiment": -43.84680600000001,
      "weight": 0.08037956702145761,
      "exit_date": "2026-06-12",
      "exit_price": 383.7200012207031,
      "pnl": -2471.2577708751473
    },
    {
      "ticker": "META",
      "side": "short",
      "entry_date": "2026-06-11",
      "entry_price": 565.8300170898438,
      "shares": 118.88480922326494,
      "notional": 67268.59363452281,
      "sentiment": -34.894687000000005,
      "weight": 0.06396862367601612,
      "exit_date": "2026-06-12",
      "exit_price": 572.9500122070312,
      "pnl": -846.4592611774139
    },
    {
      "ticker": "QQQ",
      "side": "short",
      "entry_date": "2026-06-11",
      "entry_price": 699.2899780273438,
      "shares": 69.31054120330576,
      "notional": 48468.16683512299,
      "sentiment": -25.142215999999998,
      "weight": 0.04609048230422903,
      "exit_date": "2026-06-12",
      "exit_price": 717.6099853515625,
      "pnl": -1269.769622490127
    },
    {
      "ticker": "ORCL",
      "side": "short",
      "entry_date": "2026-06-11",
      "entry_price": 179.6699981689453,
      "shares": 259.33513009439,
      "notional": 46594.74234920225,
      "sentiment": -24.170402,
      "weight": 0.04430896169482842,
      "exit_date": "2026-06-12",
      "exit_price": 185.00999450683594,
      "pnl": -1384.8486449904315
    },
    {
      "ticker": "LULU",
      "side": "short",
      "entry_date": "2026-06-11",
      "entry_price": 118.56999969482422,
      "shares": 386.66151052576527,
      "notional": 45846.45518504026,
      "sentiment": -23.782238000000003,
      "weight": 0.04359738297109386,
      "exit_date": "2026-06-12",
      "exit_price": 121.98999786376953,
      "pnl": -1322.3816579997458
    },
    {
      "ticker": "AAPL",
      "side": "short",
      "entry_date": "2026-06-11",
      "entry_price": 293.7200012207031,
      "shares": 135.52164314221378,
      "notional": 39805.41718916273,
      "sentiment": -20.648529999999997,
      "weight": 0.037852697891599625,
      "exit_date": "2026-06-12",
      "exit_price": 296.0299987792969,
      "pnl": -313.0546647951272
    },
    {
      "ticker": "SNDK",
      "side": "long",
      "entry_date": "2026-06-11",
      "entry_price": 1672.260009765625,
      "shares": 22.918194781851987,
      "notional": 38325.1806297103,
      "sentiment": 19.880677,
      "weight": 0.03644507673725312,
      "exit_date": "2026-06-12",
      "exit_price": 1890.97998046875,
      "pnl": 5012.666891255179
    },
    {
      "ticker": "HOOD",
      "side": "short",
      "entry_date": "2026-06-11",
      "entry_price": 87.08000183105469,
      "shares": 386.2207764176041,
      "notional": 33632.10591763633,
      "sentiment": -17.446207,
      "weight": 0.031982228416517336,
      "exit_date": "2026-06-12",
      "exit_price": 92.73500061035156,
      "pnl": -2184.0780191806425
    },
    {
      "ticker": "PDT",
      "side": "short",
      "entry_date": "2026-06-11",
      "entry_price": 12.84000015258789,
      "shares": 2392.841200089678,
      "notional": 30724.081374270052,
      "sentiment": -15.937708,
      "weight": 0.02921686173342754,
      "exit_date": "2026-06-12",
      "exit_price": 12.869999885559082,
      "pnl": -71.78459704515552
    },
    {
      "ticker": "MSTR",
      "side": "short",
      "entry_date": "2026-06-11",
      "entry_price": 116.11000061035156,
      "shares": 229.96108682009645,
      "notional": 26700.78193103851,
      "sentiment": -13.850675000000003,
      "weight": 0.025390931769464064,
      "exit_date": "2026-06-12",
      "exit_price": 119.48999786376953,
      "pnl": -777.267841844937
    },
    {
      "ticker": "RDDT",
      "side": "short",
      "entry_date": "2026-06-11",
      "entry_price": 168.6999969482422,
      "shares": 148.5082142769867,
      "notional": 25053.335295316552,
      "sentiment": -12.996084,
      "weight": 0.023824303300324607,
      "exit_date": "2026-06-12",
      "exit_price": 172.49000549316406,
      "pnl": -562.8474011008684
    },
    {
      "ticker": "INTC",
      "side": "short",
      "entry_date": "2026-06-11",
      "entry_price": 113.5199966430664,
      "shares": 195.9984833180087,
      "notional": 22249.747168306454,
      "sentiment": -11.54176,
      "weight": 0.02115824973580923,
      "exit_date": "2026-06-12",
      "exit_price": 117.41999816894531,
      "pnl": -764.3943840101853
    },
    {
      "ticker": "TSLA",
      "side": "short",
      "entry_date": "2026-06-11",
      "entry_price": 388.2799987792969,
      "shares": 55.935837170650615,
      "notional": 21718.76678833917,
      "sentiment": -11.266320999999998,
      "weight": 0.020653317459537534,
      "exit_date": "2026-06-12",
      "exit_price": 399.489990234375,
      "pnl": -627.0402567156348
    },
    {
      "ticker": "BTC",
      "side": "short",
      "entry_date": "2026-06-11",
      "entry_price": 27.75,
      "shares": 723.4620570036915,
      "notional": 20076.07208185244,
      "sentiment": -10.414195,
      "weight": 0.01909120780603788,
      "exit_date": "2026-06-12",
      "exit_price": 28.0,
      "pnl": -180.86551425092287
    },
    {
      "ticker": "DRAM",
      "side": "short",
      "entry_date": "2026-06-11",
      "entry_price": 59.61000061035156,
      "shares": 332.61015777900263,
      "notional": 19826.891708215477,
      "sentiment": -10.284936,
      "weight": 0.01885425137975619,
      "exit_date": "2026-06-12",
      "exit_price": 63.77000045776367,
      "pnl": -1383.6582056083687
    },
    {
      "ticker": "SMCI",
      "side": "short",
      "entry_date": "2026-06-11",
      "entry_price": 29.299999237060547,
      "shares": 652.0085004482413,
      "notional": 19103.848565690463,
      "sentiment": -9.909867,
      "weight": 0.018166678291235878,
      "exit_date": "2026-06-12",
      "exit_price": 30.760000228881836,
      "pnl": -951.9330573303437
    },
    {
      "ticker": "BMNR",
      "side": "short",
      "entry_date": "2026-06-11",
      "entry_price": 15.649999618530273,
      "shares": 1219.2280077673254,
      "notional": 19080.917856460066,
      "sentiment": -9.897972,
      "weight": 0.018144872485136333,
      "exit_date": "2026-06-12",
      "exit_price": 16.309999465942383,
      "pnl": -804.6902990870049
    },
    {
      "ticker": "NFLX",
      "side": "short",
      "entry_date": "2026-06-11",
      "entry_price": 81.87000274658203,
      "shares": 210.4125733045162,
      "notional": 17226.477954356134,
      "sentiment": -8.936005999999999,
      "weight": 0.01638140514000375,
      "exit_date": "2026-06-12",
      "exit_price": 81.58000183105469,
      "pnl": 61.019838896774026
    },
    {
      "ticker": "GOOG",
      "side": "long",
      "entry_date": "2026-06-11",
      "entry_price": 353.04998779296875,
      "shares": 46.95467396731175,
      "notional": 16577.34707098224,
      "sentiment": 8.599278,
      "weight": 0.01576411842488928,
      "exit_date": "2026-06-12",
      "exit_price": 361.1000061035156,
      "pnl": 377.9859852026183
    },
    {
      "ticker": "TSM",
      "side": "short",
      "entry_date": "2026-06-11",
      "entry_price": 413.260009765625,
      "shares": 39.336315901223095,
      "notional": 16256.126293483167,
      "sentiment": -8.432649000000001,
      "weight": 0.015458655653593731,
      "exit_date": "2026-06-12",
      "exit_price": 420.04998779296875,
      "pnl": -267.0927206459574
    },
    {
      "ticker": "AMZN",
      "side": "short",
      "entry_date": "2026-06-11",
      "entry_price": 237.92999267578125,
      "shares": 67.9888189334116,
      "notional": 16176.57919086164,
      "sentiment": -8.391385,
      "weight": 0.015383010863102639,
      "exit_date": "2026-06-12",
      "exit_price": 243.2100067138672,
      "pnl": -358.9819184012962
    },
    {
      "ticker": "SEEM",
      "side": "short",
      "entry_date": "2026-06-11",
      "entry_price": 38.189998626708984,
      "shares": 402.3485838637986,
      "notional": 15365.691865216771,
      "sentiment": -7.970748,
      "weight": 0.01461190293033315,
      "exit_date": "2026-06-12",
      "exit_price": 39.619998931884766,
      "pnl": -575.3585977122754
    }
  ],
  "entries": [
    {
      "ticker": "GOOGL",
      "side": "short",
      "entry_date": "2026-06-12",
      "entry_price": 362.6199951171875,
      "shares": 471.6289944522498,
      "notional": 171022.10366539887,
      "sentiment": -88.479187,
      "weight": 0.16504274867509772,
      "current_price": 359.6700134277344,
      "current_mark_price": 359.6700134277344,
      "current_marked_at": "2026-06-13 14:07:07 EDT",
      "current_unrealized_pnl": 1391.2968978493263,
      "current_trade_result": 1391.2968978493263,
      "current_value": 172413.4005632482
    },
    {
      "ticker": "MSFT",
      "side": "short",
      "entry_date": "2026-06-12",
      "entry_price": 391.42999267578125,
      "shares": 433.435318338818,
      "notional": 169659.58348278844,
      "sentiment": -87.77428,
      "weight": 0.16372786556207458,
      "current_price": 390.6700134277344,
      "current_mark_price": 390.6700134277344,
      "current_marked_at": "2026-06-13 14:07:07 EDT",
      "current_unrealized_pnl": 329.4018473080928,
      "current_trade_result": 329.4018473080928,
      "current_value": 169988.98533009653
    },
    {
      "ticker": "NVDA",
      "side": "short",
      "entry_date": "2026-06-12",
      "entry_price": 204.86000061035156,
      "shares": 458.71970445269164,
      "notional": 93973.3189341587,
      "sentiment": -48.617592,
      "weight": 0.09068777968817053,
      "current_price": 205.1300048828125,
      "current_mark_price": 205.1300048828125,
      "current_marked_at": "2026-06-13 14:07:07 EDT",
      "current_unrealized_pnl": -123.85628006424528,
      "current_trade_result": -123.85628006424528,
      "current_value": 93849.46265409446
    },
    {
      "ticker": "META",
      "side": "short",
      "entry_date": "2026-06-12",
      "entry_price": 572.9500122070312,
      "shares": 126.49828028024946,
      "notional": 72477.19123073739,
      "sentiment": -37.49645700000001,
      "weight": 0.06994320968226811,
      "current_price": 566.7000122070312,
      "current_mark_price": 566.7000122070312,
      "current_marked_at": "2026-06-13 14:07:07 EDT",
      "current_unrealized_pnl": 790.6142517515591,
      "current_trade_result": 790.6142517515591,
      "current_value": 73267.80548248894
    },
    {
      "ticker": "AVGO",
      "side": "short",
      "entry_date": "2026-06-12",
      "entry_price": 383.7200012207031,
      "shares": 158.00992154308446,
      "notional": 60631.56728739558,
      "sentiment": -31.368061,
      "weight": 0.058511737998317444,
      "current_price": 381.8599853515625,
      "current_mark_price": 381.8599853515625,
      "current_marked_at": "2026-06-13 14:07:07 EDT",
      "current_unrealized_pnl": 293.9009615518022,
      "current_trade_result": 293.9009615518022,
      "current_value": 60925.46824894738
    },
    {
      "ticker": "ORCL",
      "side": "short",
      "entry_date": "2026-06-12",
      "entry_price": 185.00999450683594,
      "shares": 267.58608601572314,
      "notional": 49506.100303874664,
      "sentiment": -25.612242,
      "weight": 0.04777524480883603,
      "current_price": 184.1199951171875,
      "current_mark_price": 184.1199951171875,
      "current_marked_at": "2026-06-13 14:07:07 EDT",
      "current_unrealized_pnl": 238.1514532324079,
      "current_trade_result": 238.1514532324079,
      "current_value": 49744.25175710707
    },
    {
      "ticker": "AAPL",
      "side": "short",
      "entry_date": "2026-06-12",
      "entry_price": 296.0299987792969,
      "shares": 149.68525466852284,
      "notional": 44311.32575680156,
      "sentiment": -22.924697999999996,
      "weight": 0.04276209240560173,
      "current_price": 291.0799865722656,
      "current_mark_price": 291.0799865722656,
      "current_marked_at": "2026-06-13 14:07:07 EDT",
      "current_unrealized_pnl": 740.9438378217695,
      "current_trade_result": 740.9438378217695,
      "current_value": 45052.26959462333
    },
    {
      "ticker": "QQQ",
      "side": "short",
      "entry_date": "2026-06-12",
      "entry_price": 717.6099853515625,
      "shares": 59.024033739499124,
      "notional": 42356.2359871921,
      "sentiment": -21.913221999999998,
      "weight": 0.04087535740136968,
      "current_price": 721.3200073242188,
      "current_mark_price": 721.3200073242188,
      "current_marked_at": "2026-06-13 14:07:07 EDT",
      "current_unrealized_pnl": -218.9804620883456,
      "current_trade_result": -218.9804620883456,
      "current_value": 42137.255525103756
    },
    {
      "ticker": "SNDK",
      "side": "long",
      "entry_date": "2026-06-12",
      "entry_price": 1890.97998046875,
      "shares": 15.588879768743222,
      "notional": 29478.25956062775,
      "sentiment": 15.250733000000004,
      "weight": 0.02844762682584346,
      "current_price": 1979.0400390625,
      "current_mark_price": 1979.0400390625,
      "current_marked_at": "2026-06-13 14:07:07 EDT",
      "current_unrealized_pnl": 1372.757665846452,
      "current_trade_result": 1372.757665846452,
      "current_value": 30851.017226474203
    },
    {
      "ticker": "TSLA",
      "side": "short",
      "entry_date": "2026-06-12",
      "entry_price": 399.489990234375,
      "shares": 66.95640118094762,
      "notional": 26748.41205390566,
      "sentiment": -13.838431999999997,
      "weight": 0.02581322152783151,
      "current_price": 406.44500732421875,
      "current_mark_price": 406.44500732421875,
      "current_marked_at": "2026-06-13 14:07:07 EDT",
      "current_unrealized_pnl": -465.68291448792496,
      "current_trade_result": -465.68291448792496,
      "current_value": 26282.729139417734
    },
    {
      "ticker": "RDDT",
      "side": "short",
      "entry_date": "2026-06-12",
      "entry_price": 172.49000549316406,
      "shares": 145.63296597647036,
      "notional": 25120.23110126715,
      "sentiment": -12.996084,
      "weight": 0.024241965801205415,
      "current_price": 162.17999267578125,
      "current_mark_price": 162.17999267578125,
      "current_marked_at": "2026-06-13 14:07:07 EDT",
      "current_unrealized_pnl": 1501.4777458508845,
      "current_trade_result": 1501.4777458508845,
      "current_value": 26621.708847118032
    },
    {
      "ticker": "MSTR",
      "side": "short",
      "entry_date": "2026-06-12",
      "entry_price": 119.48999786376953,
      "shares": 192.1164236518058,
      "notional": 22955.99105174932,
      "sentiment": -11.876403000000002,
      "weight": 0.022153392927233576,
      "current_price": 123.95999908447266,
      "current_mark_price": 123.95999908447266,
      "current_marked_at": "2026-06-13 14:07:07 EDT",
      "current_unrealized_pnl": -858.7606482406907,
      "current_trade_result": -858.7606482406907,
      "current_value": 22097.230403508627
    },
    {
      "ticker": "AMZN",
      "side": "short",
      "entry_date": "2026-06-12",
      "entry_price": 243.2100067138672,
      "shares": 85.87152721403544,
      "notional": 20884.81471025559,
      "sentiment": -10.804869,
      "weight": 0.02015463002428305,
      "current_price": 238.52999877929688,
      "current_mark_price": 238.52999877929688,
      "current_marked_at": "2026-06-13 14:07:07 EDT",
      "current_unrealized_pnl": 401.87942871535637,
      "current_trade_result": 401.87942871535637,
      "current_value": 21286.694138970946
    },
    {
      "ticker": "TSM",
      "side": "short",
      "entry_date": "2026-06-12",
      "entry_price": 420.04998779296875,
      "shares": 46.949706379344,
      "notional": 19721.223591526916,
      "sentiment": -10.202879,
      "weight": 0.019031720923921153,
      "current_price": 423.7799987792969,
      "current_mark_price": 423.7799987792969,
      "current_marked_at": "2026-06-13 14:07:07 EDT",
      "current_unrealized_pnl": -175.12292059983278,
      "current_trade_result": -175.12292059983278,
      "current_value": 19546.100670927084
    },
    {
      "ticker": "PDT",
      "side": "short",
      "entry_date": "2026-06-12",
      "entry_price": 12.869999885559082,
      "shares": 1508.7795700698932,
      "notional": 19417.992894133407,
      "sentiment": -10.046001,
      "weight": 0.01873909192037197,
      "current_price": 12.789999961853027,
      "current_mark_price": 12.789999961853027,
      "current_marked_at": "2026-06-13 14:07:07 EDT",
      "current_unrealized_pnl": 120.70225049484544,
      "current_trade_result": 120.70225049484544,
      "current_value": 19538.695144628255
    },
    {
      "ticker": "SMCI",
      "side": "short",
      "entry_date": "2026-06-12",
      "entry_price": 30.760000228881836,
      "shares": 622.7197104020468,
      "notional": 19154.85843449619,
      "sentiment": -9.909867,
      "weight": 0.018485157291111238,
      "current_price": 30.459999084472656,
      "current_mark_price": 30.459999084472656,
      "current_marked_at": "2026-06-13 14:07:07 EDT",
      "current_unrealized_pnl": 186.81662576676698,
      "current_trade_result": 186.81662576676698,
      "current_value": 19341.675060262955
    },
    {
      "ticker": "BMNR",
      "side": "short",
      "entry_date": "2026-06-12",
      "entry_price": 16.309999465942383,
      "shares": 1173.014538541809,
      "notional": 19131.866497159557,
      "sentiment": -9.897972,
      "weight": 0.018462969208669994,
      "current_price": 16.103500366210938,
      "current_mark_price": 16.103500366210938,
      "current_marked_at": "2026-06-13 14:07:07 EDT",
      "current_unrealized_pnl": 242.22644618078033,
      "current_trade_result": 242.22644618078033,
      "current_value": 19374.092943340336
    },
    {
      "ticker": "ARR",
      "side": "long",
      "entry_date": "2026-06-12",
      "entry_price": 17.209999084472656,
      "shares": 1098.8318163650513,
      "notional": 18910.89455363196,
      "sentiment": 9.783651,
      "weight": 0.018249722989858268,
      "current_price": 17.104999542236328,
      "current_mark_price": 17.104999542236328,
      "current_marked_at": "2026-06-13 14:07:07 EDT",
      "current_unrealized_pnl": -115.37683771304336,
      "current_trade_result": -115.37683771304336,
      "current_value": 18795.517715918915
    },
    {
      "ticker": "MU",
      "side": "long",
      "entry_date": "2026-06-12",
      "entry_price": 971.8099975585938,
      "shares": 18.74233302150852,
      "notional": 18213.986607874547,
      "sentiment": 9.423102,
      "weight": 0.017577180666520035,
      "current_price": 980.7100219726562,
      "current_mark_price": 980.7100219726562,
      "current_marked_at": "2026-06-13 14:07:07 EDT",
      "current_unrealized_pnl": 166.8072214679156,
      "current_trade_result": 166.8072214679156,
      "current_value": 18380.793829342463
    },
    {
      "ticker": "INTC",
      "side": "short",
      "entry_date": "2026-06-12",
      "entry_price": 117.41999816894531,
      "shares": 149.73486688960068,
      "notional": 17581.867796004182,
      "sentiment": -9.096072,
      "weight": 0.0169671622889866,
      "current_price": 124.54000091552734,
      "current_mark_price": 124.54000091552734,
      "current_marked_at": "2026-06-13 14:07:07 EDT",
      "current_unrealized_pnl": -1066.1126635130518,
      "current_trade_result": -1066.1126635130518,
      "current_value": 16515.75513249113
    },
    {
      "ticker": "IPOS",
      "side": "short",
      "entry_date": "2026-06-12",
      "entry_price": 23.399999618530273,
      "shares": 681.1424841484738,
      "notional": 15938.73386923905,
      "sentiment": -8.245988,
      "weight": 0.015381476381127596,
      "current_price": 23.6643009185791,
      "current_mark_price": 23.6643009185791,
      "current_marked_at": "2026-06-13 14:07:07 EDT",
      "current_unrealized_pnl": -180.02684407892994,
      "current_trade_result": -180.02684407892994,
      "current_value": 15758.70702516012
    },
    {
      "ticker": "TGT",
      "side": "short",
      "entry_date": "2026-06-12",
      "entry_price": 133.4499969482422,
      "shares": 119.1846136123099,
      "notional": 15905.186322840182,
      "sentiment": -8.228632000000001,
      "weight": 0.01534910173977827,
      "current_price": 135.22000122070312,
      "current_mark_price": 135.22000122070312,
      "current_marked_at": "2026-06-13 14:07:07 EDT",
      "current_unrealized_pnl": -210.95727530539455,
      "current_trade_result": -210.95727530539455,
      "current_value": 15694.229047534787
    },
    {
      "ticker": "NFLX",
      "side": "short",
      "entry_date": "2026-06-12",
      "entry_price": 81.58000183105469,
      "shares": 189.63584733281894,
      "notional": 15470.492772644977,
      "sentiment": -8.003741,
      "weight": 0.014929606149337419,
      "current_price": 80.33499908447266,
      "current_mark_price": 80.33499908447266,
      "current_marked_at": "2026-06-13 14:07:07 EDT",
      "current_unrealized_pnl": 236.09715077977035,
      "current_trade_result": 236.09715077977035,
      "current_value": 15706.589923424748
    },
    {
      "ticker": "COLA",
      "side": "long",
      "entry_date": "2026-06-12",
      "entry_price": 10.779999732971191,
      "shares": 1293.6284679931352,
      "notional": 13945.314539529929,
      "sentiment": 7.214682,
      "weight": 0.013457751912851002,
      "current_price": 10.645000457763672,
      "current_mark_price": 10.645000457763672,
      "current_marked_at": "2026-06-13 14:07:07 EDT",
      "current_unrealized_pnl": -174.63890556688713,
      "current_trade_result": -174.63890556688713,
      "current_value": 13770.675633963041
    },
    {
      "ticker": "LULU",
      "side": "short",
      "entry_date": "2026-06-12",
      "entry_price": 121.98999786376953,
      "shares": 112.39918010179741,
      "notional": 13711.575740507713,
      "sentiment": -7.093756,
      "weight": 0.013232185199333562,
      "current_price": 118.76000213623047,
      "current_mark_price": 118.76000213623047,
      "current_marked_at": "2026-06-13 14:07:07 EDT",
      "current_unrealized_pnl": 363.04887150769923,
      "current_trade_result": 363.04887150769923,
      "current_value": 14074.624612015412
    }
  ],
  "positions": {
    "long": {
      "SNDK": {
        "ticker": "SNDK",
        "side": "long",
        "entry_date": "2026-06-12",
        "entry_price": 1890.97998046875,
        "shares": 15.588879768743222,
        "notional": 29478.25956062775,
        "sentiment": 15.250733000000004,
        "weight": 0.02844762682584346,
        "current_price": 1979.0400390625,
        "current_mark_price": 1979.0400390625,
        "current_marked_at": "2026-06-13 14:07:07 EDT",
        "current_unrealized_pnl": 1372.757665846452,
        "current_trade_result": 1372.757665846452,
        "current_value": 30851.017226474203
      },
      "ARR": {
        "ticker": "ARR",
        "side": "long",
        "entry_date": "2026-06-12",
        "entry_price": 17.209999084472656,
        "shares": 1098.8318163650513,
        "notional": 18910.89455363196,
        "sentiment": 9.783651,
        "weight": 0.018249722989858268,
        "current_price": 17.104999542236328,
        "current_mark_price": 17.104999542236328,
        "current_marked_at": "2026-06-13 14:07:07 EDT",
        "current_unrealized_pnl": -115.37683771304336,
        "current_trade_result": -115.37683771304336,
        "current_value": 18795.517715918915
      },
      "MU": {
        "ticker": "MU",
        "side": "long",
        "entry_date": "2026-06-12",
        "entry_price": 971.8099975585938,
        "shares": 18.74233302150852,
        "notional": 18213.986607874547,
        "sentiment": 9.423102,
        "weight": 0.017577180666520035,
        "current_price": 980.7100219726562,
        "current_mark_price": 980.7100219726562,
        "current_marked_at": "2026-06-13 14:07:07 EDT",
        "current_unrealized_pnl": 166.8072214679156,
        "current_trade_result": 166.8072214679156,
        "current_value": 18380.793829342463
      },
      "COLA": {
        "ticker": "COLA",
        "side": "long",
        "entry_date": "2026-06-12",
        "entry_price": 10.779999732971191,
        "shares": 1293.6284679931352,
        "notional": 13945.314539529929,
        "sentiment": 7.214682,
        "weight": 0.013457751912851002,
        "current_price": 10.645000457763672,
        "current_mark_price": 10.645000457763672,
        "current_marked_at": "2026-06-13 14:07:07 EDT",
        "current_unrealized_pnl": -174.63890556688713,
        "current_trade_result": -174.63890556688713,
        "current_value": 13770.675633963041
      }
    },
    "short": {
      "GOOGL": {
        "ticker": "GOOGL",
        "side": "short",
        "entry_date": "2026-06-12",
        "entry_price": 362.6199951171875,
        "shares": 471.6289944522498,
        "notional": 171022.10366539887,
        "sentiment": -88.479187,
        "weight": 0.16504274867509772,
        "current_price": 359.6700134277344,
        "current_mark_price": 359.6700134277344,
        "current_marked_at": "2026-06-13 14:07:07 EDT",
        "current_unrealized_pnl": 1391.2968978493263,
        "current_trade_result": 1391.2968978493263,
        "current_value": 172413.4005632482
      },
      "MSFT": {
        "ticker": "MSFT",
        "side": "short",
        "entry_date": "2026-06-12",
        "entry_price": 391.42999267578125,
        "shares": 433.435318338818,
        "notional": 169659.58348278844,
        "sentiment": -87.77428,
        "weight": 0.16372786556207458,
        "current_price": 390.6700134277344,
        "current_mark_price": 390.6700134277344,
        "current_marked_at": "2026-06-13 14:07:07 EDT",
        "current_unrealized_pnl": 329.4018473080928,
        "current_trade_result": 329.4018473080928,
        "current_value": 169988.98533009653
      },
      "NVDA": {
        "ticker": "NVDA",
        "side": "short",
        "entry_date": "2026-06-12",
        "entry_price": 204.86000061035156,
        "shares": 458.71970445269164,
        "notional": 93973.3189341587,
        "sentiment": -48.617592,
        "weight": 0.09068777968817053,
        "current_price": 205.1300048828125,
        "current_mark_price": 205.1300048828125,
        "current_marked_at": "2026-06-13 14:07:07 EDT",
        "current_unrealized_pnl": -123.85628006424528,
        "current_trade_result": -123.85628006424528,
        "current_value": 93849.46265409446
      },
      "META": {
        "ticker": "META",
        "side": "short",
        "entry_date": "2026-06-12",
        "entry_price": 572.9500122070312,
        "shares": 126.49828028024946,
        "notional": 72477.19123073739,
        "sentiment": -37.49645700000001,
        "weight": 0.06994320968226811,
        "current_price": 566.7000122070312,
        "current_mark_price": 566.7000122070312,
        "current_marked_at": "2026-06-13 14:07:07 EDT",
        "current_unrealized_pnl": 790.6142517515591,
        "current_trade_result": 790.6142517515591,
        "current_value": 73267.80548248894
      },
      "AVGO": {
        "ticker": "AVGO",
        "side": "short",
        "entry_date": "2026-06-12",
        "entry_price": 383.7200012207031,
        "shares": 158.00992154308446,
        "notional": 60631.56728739558,
        "sentiment": -31.368061,
        "weight": 0.058511737998317444,
        "current_price": 381.8599853515625,
        "current_mark_price": 381.8599853515625,
        "current_marked_at": "2026-06-13 14:07:07 EDT",
        "current_unrealized_pnl": 293.9009615518022,
        "current_trade_result": 293.9009615518022,
        "current_value": 60925.46824894738
      },
      "ORCL": {
        "ticker": "ORCL",
        "side": "short",
        "entry_date": "2026-06-12",
        "entry_price": 185.00999450683594,
        "shares": 267.58608601572314,
        "notional": 49506.100303874664,
        "sentiment": -25.612242,
        "weight": 0.04777524480883603,
        "current_price": 184.1199951171875,
        "current_mark_price": 184.1199951171875,
        "current_marked_at": "2026-06-13 14:07:07 EDT",
        "current_unrealized_pnl": 238.1514532324079,
        "current_trade_result": 238.1514532324079,
        "current_value": 49744.25175710707
      },
      "AAPL": {
        "ticker": "AAPL",
        "side": "short",
        "entry_date": "2026-06-12",
        "entry_price": 296.0299987792969,
        "shares": 149.68525466852284,
        "notional": 44311.32575680156,
        "sentiment": -22.924697999999996,
        "weight": 0.04276209240560173,
        "current_price": 291.0799865722656,
        "current_mark_price": 291.0799865722656,
        "current_marked_at": "2026-06-13 14:07:07 EDT",
        "current_unrealized_pnl": 740.9438378217695,
        "current_trade_result": 740.9438378217695,
        "current_value": 45052.26959462333
      },
      "QQQ": {
        "ticker": "QQQ",
        "side": "short",
        "entry_date": "2026-06-12",
        "entry_price": 717.6099853515625,
        "shares": 59.024033739499124,
        "notional": 42356.2359871921,
        "sentiment": -21.913221999999998,
        "weight": 0.04087535740136968,
        "current_price": 721.3200073242188,
        "current_mark_price": 721.3200073242188,
        "current_marked_at": "2026-06-13 14:07:07 EDT",
        "current_unrealized_pnl": -218.9804620883456,
        "current_trade_result": -218.9804620883456,
        "current_value": 42137.255525103756
      },
      "TSLA": {
        "ticker": "TSLA",
        "side": "short",
        "entry_date": "2026-06-12",
        "entry_price": 399.489990234375,
        "shares": 66.95640118094762,
        "notional": 26748.41205390566,
        "sentiment": -13.838431999999997,
        "weight": 0.02581322152783151,
        "current_price": 406.44500732421875,
        "current_mark_price": 406.44500732421875,
        "current_marked_at": "2026-06-13 14:07:07 EDT",
        "current_unrealized_pnl": -465.68291448792496,
        "current_trade_result": -465.68291448792496,
        "current_value": 26282.729139417734
      },
      "RDDT": {
        "ticker": "RDDT",
        "side": "short",
        "entry_date": "2026-06-12",
        "entry_price": 172.49000549316406,
        "shares": 145.63296597647036,
        "notional": 25120.23110126715,
        "sentiment": -12.996084,
        "weight": 0.024241965801205415,
        "current_price": 162.17999267578125,
        "current_mark_price": 162.17999267578125,
        "current_marked_at": "2026-06-13 14:07:07 EDT",
        "current_unrealized_pnl": 1501.4777458508845,
        "current_trade_result": 1501.4777458508845,
        "current_value": 26621.708847118032
      },
      "MSTR": {
        "ticker": "MSTR",
        "side": "short",
        "entry_date": "2026-06-12",
        "entry_price": 119.48999786376953,
        "shares": 192.1164236518058,
        "notional": 22955.99105174932,
        "sentiment": -11.876403000000002,
        "weight": 0.022153392927233576,
        "current_price": 123.95999908447266,
        "current_mark_price": 123.95999908447266,
        "current_marked_at": "2026-06-13 14:07:07 EDT",
        "current_unrealized_pnl": -858.7606482406907,
        "current_trade_result": -858.7606482406907,
        "current_value": 22097.230403508627
      },
      "AMZN": {
        "ticker": "AMZN",
        "side": "short",
        "entry_date": "2026-06-12",
        "entry_price": 243.2100067138672,
        "shares": 85.87152721403544,
        "notional": 20884.81471025559,
        "sentiment": -10.804869,
        "weight": 0.02015463002428305,
        "current_price": 238.52999877929688,
        "current_mark_price": 238.52999877929688,
        "current_marked_at": "2026-06-13 14:07:07 EDT",
        "current_unrealized_pnl": 401.87942871535637,
        "current_trade_result": 401.87942871535637,
        "current_value": 21286.694138970946
      },
      "TSM": {
        "ticker": "TSM",
        "side": "short",
        "entry_date": "2026-06-12",
        "entry_price": 420.04998779296875,
        "shares": 46.949706379344,
        "notional": 19721.223591526916,
        "sentiment": -10.202879,
        "weight": 0.019031720923921153,
        "current_price": 423.7799987792969,
        "current_mark_price": 423.7799987792969,
        "current_marked_at": "2026-06-13 14:07:07 EDT",
        "current_unrealized_pnl": -175.12292059983278,
        "current_trade_result": -175.12292059983278,
        "current_value": 19546.100670927084
      },
      "PDT": {
        "ticker": "PDT",
        "side": "short",
        "entry_date": "2026-06-12",
        "entry_price": 12.869999885559082,
        "shares": 1508.7795700698932,
        "notional": 19417.992894133407,
        "sentiment": -10.046001,
        "weight": 0.01873909192037197,
        "current_price": 12.789999961853027,
        "current_mark_price": 12.789999961853027,
        "current_marked_at": "2026-06-13 14:07:07 EDT",
        "current_unrealized_pnl": 120.70225049484544,
        "current_trade_result": 120.70225049484544,
        "current_value": 19538.695144628255
      },
      "SMCI": {
        "ticker": "SMCI",
        "side": "short",
        "entry_date": "2026-06-12",
        "entry_price": 30.760000228881836,
        "shares": 622.7197104020468,
        "notional": 19154.85843449619,
        "sentiment": -9.909867,
        "weight": 0.018485157291111238,
        "current_price": 30.459999084472656,
        "current_mark_price": 30.459999084472656,
        "current_marked_at": "2026-06-13 14:07:07 EDT",
        "current_unrealized_pnl": 186.81662576676698,
        "current_trade_result": 186.81662576676698,
        "current_value": 19341.675060262955
      },
      "BMNR": {
        "ticker": "BMNR",
        "side": "short",
        "entry_date": "2026-06-12",
        "entry_price": 16.309999465942383,
        "shares": 1173.014538541809,
        "notional": 19131.866497159557,
        "sentiment": -9.897972,
        "weight": 0.018462969208669994,
        "current_price": 16.103500366210938,
        "current_mark_price": 16.103500366210938,
        "current_marked_at": "2026-06-13 14:07:07 EDT",
        "current_unrealized_pnl": 242.22644618078033,
        "current_trade_result": 242.22644618078033,
        "current_value": 19374.092943340336
      },
      "INTC": {
        "ticker": "INTC",
        "side": "short",
        "entry_date": "2026-06-12",
        "entry_price": 117.41999816894531,
        "shares": 149.73486688960068,
        "notional": 17581.867796004182,
        "sentiment": -9.096072,
        "weight": 0.0169671622889866,
        "current_price": 124.54000091552734,
        "current_mark_price": 124.54000091552734,
        "current_marked_at": "2026-06-13 14:07:07 EDT",
        "current_unrealized_pnl": -1066.1126635130518,
        "current_trade_result": -1066.1126635130518,
        "current_value": 16515.75513249113
      },
      "IPOS": {
        "ticker": "IPOS",
        "side": "short",
        "entry_date": "2026-06-12",
        "entry_price": 23.399999618530273,
        "shares": 681.1424841484738,
        "notional": 15938.73386923905,
        "sentiment": -8.245988,
        "weight": 0.015381476381127596,
        "current_price": 23.6643009185791,
        "current_mark_price": 23.6643009185791,
        "current_marked_at": "2026-06-13 14:07:07 EDT",
        "current_unrealized_pnl": -180.02684407892994,
        "current_trade_result": -180.02684407892994,
        "current_value": 15758.70702516012
      },
      "TGT": {
        "ticker": "TGT",
        "side": "short",
        "entry_date": "2026-06-12",
        "entry_price": 133.4499969482422,
        "shares": 119.1846136123099,
        "notional": 15905.186322840182,
        "sentiment": -8.228632000000001,
        "weight": 0.01534910173977827,
        "current_price": 135.22000122070312,
        "current_mark_price": 135.22000122070312,
        "current_marked_at": "2026-06-13 14:07:07 EDT",
        "current_unrealized_pnl": -210.95727530539455,
        "current_trade_result": -210.95727530539455,
        "current_value": 15694.229047534787
      },
      "NFLX": {
        "ticker": "NFLX",
        "side": "short",
        "entry_date": "2026-06-12",
        "entry_price": 81.58000183105469,
        "shares": 189.63584733281894,
        "notional": 15470.492772644977,
        "sentiment": -8.003741,
        "weight": 0.014929606149337419,
        "current_price": 80.33499908447266,
        "current_mark_price": 80.33499908447266,
        "current_marked_at": "2026-06-13 14:07:07 EDT",
        "current_unrealized_pnl": 236.09715077977035,
        "current_trade_result": 236.09715077977035,
        "current_value": 15706.589923424748
      },
      "LULU": {
        "ticker": "LULU",
        "side": "short",
        "entry_date": "2026-06-12",
        "entry_price": 121.98999786376953,
        "shares": 112.39918010179741,
        "notional": 13711.575740507713,
        "sentiment": -7.093756,
        "weight": 0.013232185199333562,
        "current_price": 118.76000213623047,
        "current_mark_price": 118.76000213623047,
        "current_marked_at": "2026-06-13 14:07:07 EDT",
        "current_unrealized_pnl": 363.04887150769923,
        "current_trade_result": 363.04887150769923,
        "current_value": 14074.624612015412
      }
    }
  },
  "planned_only": true,
  "trade_status": "open_mark_to_market",
  "trade_close_time": "2026-06-15 09:30:00 EDT",
  "current_marked_at": "2026-06-13 14:07:07 EDT",
  "current_unrealized_pnl": 4786.606904467082,
  "current_trade_result": 4786.606904467082,
  "marked_account_value": 1041015.7356502085,
  "today_profit": -10571.585896994904,
  "total_profit": 41015.735650208524,
  "total_investment": 1041015.7356502085
}