{
  "date": "2026-06-02",
  "next_trade_date": "2026-06-03",
  "starting_value": 999269.1424376859,
  "realized_pnl": 42838.11135976568,
  "ending_value_before_rebalance": 1042107.2537974515,
  "allocated_value": 1042107.2537974514,
  "cash_after_rebalance": 1.1641532182693481e-10,
  "exits": [
    {
      "ticker": "MSFT",
      "side": "short",
      "entry_date": "2026-06-01",
      "entry_price": 464.8399963378906,
      "shares": 268.48376818421286,
      "notional": 124801.9938195326,
      "sentiment": -50.941698,
      "weight": 0.12489327301259602,
      "exit_date": "2026-06-02",
      "exit_price": 446.8800048828125,
      "pnl": 4821.966182415639
    },
    {
      "ticker": "DELL",
      "side": "long",
      "entry_date": "2026-06-01",
      "entry_price": 426.1499938964844,
      "shares": 267.06884961790405,
      "notional": 113811.3886346109,
      "sentiment": 46.455551,
      "weight": 0.11389462938580448,
      "exit_date": "2026-06-02",
      "exit_price": 466.1099853515625,
      "pnl": 10672.06894864899
    },
    {
      "ticker": "META",
      "side": "short",
      "entry_date": "2026-06-01",
      "entry_price": 630.4000244140625,
      "shares": 172.4920323601199,
      "notional": 108738.98141105085,
      "sentiment": -44.38509499999999,
      "weight": 0.10881851224364389,
      "exit_date": "2026-06-02",
      "exit_price": 603.239990234375,
      "pnl": 4684.889494624619
    },
    {
      "ticker": "CRSR",
      "side": "long",
      "entry_date": "2026-06-01",
      "entry_price": 10.324999809265137,
      "shares": 7603.386510713327,
      "notional": 78504.96427288422,
      "sentiment": 32.044169,
      "weight": 0.07856238218401682,
      "exit_date": "2026-06-02",
      "exit_price": 11.119999885559082,
      "pnl": 6044.692856109449
    },
    {
      "ticker": "TGT",
      "side": "long",
      "entry_date": "2026-06-01",
      "entry_price": 126.4800033569336,
      "shares": 418.5818975932181,
      "notional": 52942.239812741864,
      "sentiment": 21.609972,
      "weight": 0.05298096134900245,
      "exit_date": "2026-06-02",
      "exit_price": 123.2300033569336,
      "pnl": -1360.3911671779588
    },
    {
      "ticker": "RIVN",
      "side": "long",
      "entry_date": "2026-06-01",
      "entry_price": 16.139999389648438,
      "shares": 2384.866769408414,
      "notional": 38491.74820264464,
      "sentiment": 15.711568,
      "weight": 0.03851990076341717,
      "exit_date": "2026-06-02",
      "exit_price": 16.989999771118164,
      "pnl": 2027.1376637516262
    },
    {
      "ticker": "GME",
      "side": "short",
      "entry_date": "2026-06-01",
      "entry_price": 21.020000457763672,
      "shares": 1773.7277020206718,
      "notional": 37283.75710842263,
      "sentiment": -15.21849,
      "weight": 0.03731102615404502,
      "exit_date": "2026-06-02",
      "exit_price": 21.139999389648438,
      "pnl": -212.84542969690045
    },
    {
      "ticker": "HPE",
      "side": "long",
      "entry_date": "2026-06-01",
      "entry_price": 44.18000030517578,
      "shares": 757.2064200755058,
      "notional": 33453.379870016906,
      "sentiment": 13.655006,
      "weight": 0.033477847407965014,
      "exit_date": "2026-06-02",
      "exit_price": 63.060001373291016,
      "pnl": 14296.058019809261
    },
    {
      "ticker": "SNDK",
      "side": "long",
      "entry_date": "2026-06-01",
      "entry_price": 1731.1500244140625,
      "shares": 18.790786268652365,
      "notional": 32529.670107736973,
      "sentiment": 13.277966000000003,
      "weight": 0.032553462051656934,
      "exit_date": "2026-06-02",
      "exit_price": 1750.06005859375,
      "pnl": 355.33441060341875
    },
    {
      "ticker": "HOOD",
      "side": "short",
      "entry_date": "2026-06-01",
      "entry_price": 89.94000244140625,
      "shares": 358.4989018590961,
      "notional": 32243.392108448566,
      "sentiment": -13.161113,
      "weight": 0.03226697467089979,
      "exit_date": "2026-06-02",
      "exit_price": 88.66999816894531,
      "pnl": 455.2951370336064
    },
    {
      "ticker": "NVDA",
      "side": "long",
      "entry_date": "2026-06-01",
      "entry_price": 215.72999572753906,
      "shares": 136.6538308139595,
      "notional": 29480.330337647327,
      "sentiment": 12.033286,
      "weight": 0.029501892018531647,
      "exit_date": "2026-06-02",
      "exit_price": 227.17999267578125,
      "pnl": 1564.6859457854405
    },
    {
      "ticker": "GOOGL",
      "side": "short",
      "entry_date": "2026-06-01",
      "entry_price": 376.5199890136719,
      "shares": 78.13164844090126,
      "notional": 29418.127412588216,
      "sentiment": -12.007896,
      "weight": 0.02943964359874419,
      "exit_date": "2026-06-02",
      "exit_price": 366.5899963378906,
      "pnl": 775.846696764865
    },
    {
      "ticker": "JAN",
      "side": "short",
      "entry_date": "2026-06-01",
      "entry_price": 25.56999969482422,
      "shares": 1093.8141959835555,
      "notional": 27968.828657493912,
      "sentiment": -11.416321,
      "weight": 0.027989284837981514,
      "exit_date": "2026-06-02",
      "exit_price": 25.860000610351562,
      "pnl": -317.2071182520365
    },
    {
      "ticker": "QQQ",
      "side": "short",
      "entry_date": "2026-06-01",
      "entry_price": 737.0399780273438,
      "shares": 34.34828452429847,
      "notional": 25316.058871065896,
      "sentiment": -10.333513,
      "weight": 0.025334574836673292,
      "exit_date": "2026-06-02",
      "exit_price": 742.4000244140625,
      "pnl": -184.10839835445358
    },
    {
      "ticker": "ZM",
      "side": "long",
      "entry_date": "2026-06-01",
      "entry_price": 104.0,
      "shares": 240.53669663313602,
      "notional": 25015.816449846145,
      "sentiment": 10.21096,
      "weight": 0.025034112820516846,
      "exit_date": "2026-06-02",
      "exit_price": 108.29000091552734,
      "pnl": 1031.9026487740764
    },
    {
      "ticker": "NOW",
      "side": "long",
      "entry_date": "2026-06-01",
      "entry_price": 135.77000427246094,
      "shares": 179.97387141548293,
      "notional": 24435.053291011453,
      "sentiment": 9.973904000000001,
      "weight": 0.02445292489609246,
      "exit_date": "2026-06-02",
      "exit_price": 129.89999389648438,
      "pnl": -1056.4484926135565
    },
    {
      "ticker": "ASTS",
      "side": "short",
      "entry_date": "2026-06-01",
      "entry_price": 108.66999816894531,
      "shares": 205.8406989597162,
      "notional": 22368.708379046784,
      "sentiment": -9.130462999999999,
      "weight": 0.02238506867577139,
      "exit_date": "2026-06-02",
      "exit_price": 109.91000366210938,
      "pnl": -255.24359742677822
    },
    {
      "ticker": "SNOW",
      "side": "long",
      "entry_date": "2026-06-01",
      "entry_price": 259.9700012207031,
      "shares": 84.988712642726,
      "notional": 22094.515729475464,
      "sentiment": 9.018543,
      "weight": 0.02211067548386072,
      "exit_date": "2026-06-02",
      "exit_price": 265.45001220703125,
      "pnl": 465.7390789960225
    },
    {
      "ticker": "AVGO",
      "side": "short",
      "entry_date": "2026-06-01",
      "entry_price": 450.0899963378906,
      "shares": 48.360363781454545,
      "notional": 21766.515957293934,
      "sentiment": -8.88466,
      "weight": 0.021782435815235122,
      "exit_date": "2026-06-02",
      "exit_price": 488.7900085449219,
      "pnl": -1871.546668678763
    },
    {
      "ticker": "TSLA",
      "side": "short",
      "entry_date": "2026-06-01",
      "entry_price": 427.489990234375,
      "shares": 49.28756619780379,
      "notional": 21069.941192575254,
      "sentiment": -8.600332,
      "weight": 0.02108535158123245,
      "exit_date": "2026-06-02",
      "exit_price": 418.2200012207031,
      "pnl": 456.8951971642664
    },
    {
      "ticker": "UBER",
      "side": "short",
      "entry_date": "2026-06-01",
      "entry_price": 71.33000183105469,
      "shares": 290.82740884435157,
      "notional": 20744.719605388487,
      "sentiment": -8.467583000000001,
      "weight": 0.02075989212954419,
      "exit_date": "2026-06-02",
      "exit_price": 72.5999984741211,
      "pnl": -369.34983294402775
    },
    {
      "ticker": "ADDS",
      "side": "long",
      "entry_date": "2026-06-01",
      "entry_price": 24.940000534057617,
      "shares": 782.2823654673422,
      "notional": 19510.12261253937,
      "sentiment": 7.963645,
      "weight": 0.019524392162200702,
      "exit_date": "2026-06-02",
      "exit_price": 26.329999923706055,
      "pnl": 1087.3720105323416
    },
    {
      "ticker": "LLY",
      "side": "long",
      "entry_date": "2026-06-01",
      "entry_price": 1095.0,
      "shares": 17.578977691988495,
      "notional": 19248.980572727403,
      "sentiment": 7.857052,
      "weight": 0.01926305912516233,
      "exit_date": "2026-06-02",
      "exit_price": 1067.3699951171875,
      "pnl": -485.70723946449414
    },
    {
      "ticker": "ARR",
      "side": "long",
      "entry_date": "2026-06-01",
      "entry_price": 17.0,
      "shares": 1121.3927996173866,
      "notional": 19063.677593495573,
      "sentiment": 7.781415,
      "weight": 0.019077620616794317,
      "exit_date": "2026-06-02",
      "exit_price": 17.110000610351562,
      "pnl": 123.35389240175995
    },
    {
      "ticker": "SIZE",
      "side": "long",
      "entry_date": "2026-06-01",
      "entry_price": 175.1300048828125,
      "shares": 108.29800661566688,
      "notional": 18966.230427400602,
      "sentiment": 7.741638999999999,
      "weight": 0.018980102178611336,
      "exit_date": "2026-06-02",
      "exit_price": 175.94000244140625,
      "pnl": 87.72112095925996
    }
  ],
  "entries": [
    {
      "ticker": "DELL",
      "side": "long",
      "entry_date": "2026-06-02",
      "entry_price": 466.1099853515625,
      "shares": 276.5659700702741,
      "notional": 128910.16025819612,
      "sentiment": 57.651451,
      "weight": 0.12370143263895912
    },
    {
      "ticker": "MSFT",
      "side": "short",
      "entry_date": "2026-06-02",
      "entry_price": 446.8800048828125,
      "shares": 265.39348645830177,
      "notional": 118599.04252435254,
      "sentiment": -53.040093000000006,
      "weight": 0.11380694462319131
    },
    {
      "ticker": "META",
      "side": "short",
      "entry_date": "2026-06-02",
      "entry_price": 603.239990234375,
      "shares": 187.19685570659806,
      "notional": 112924.62940835393,
      "sentiment": -50.502371,
      "weight": 0.10836181112534742
    },
    {
      "ticker": "CRSR",
      "side": "long",
      "entry_date": "2026-06-02",
      "entry_price": 11.119999885559082,
      "shares": 6813.972891042895,
      "notional": 75771.37776859968,
      "sentiment": 33.886621999999996,
      "weight": 0.07270976906886298
    },
    {
      "ticker": "HPE",
      "side": "long",
      "entry_date": "2026-06-02",
      "entry_price": 63.060001373291016,
      "shares": 988.3475700138507,
      "notional": 62325.19912236226,
      "sentiment": 27.873196,
      "weight": 0.05980689501512294
    },
    {
      "ticker": "SPCE",
      "side": "short",
      "entry_date": "2026-06-02",
      "entry_price": 6.739999771118164,
      "shares": 6860.204871306986,
      "notional": 46237.7792624328,
      "sentiment": -20.678549,
      "weight": 0.044369501405869476
    },
    {
      "ticker": "RIVN",
      "side": "long",
      "entry_date": "2026-06-02",
      "entry_price": 16.989999771118164,
      "shares": 2183.0696127016336,
      "notional": 37090.35222013577,
      "sentiment": 16.587619,
      "weight": 0.035591684142853894
    },
    {
      "ticker": "GOOGL",
      "side": "short",
      "entry_date": "2026-06-02",
      "entry_price": 366.5899963378906,
      "shares": 99.68814534151198,
      "notional": 36544.676835675986,
      "sentiment": -16.343581,
      "weight": 0.03506805724891247
    },
    {
      "ticker": "NVDA",
      "side": "long",
      "entry_date": "2026-06-02",
      "entry_price": 227.17999267578125,
      "shares": 156.41749502552216,
      "notional": 35534.92537426217,
      "sentiment": 15.891998000000001,
      "weight": 0.03409910567724433
    },
    {
      "ticker": "SNDK",
      "side": "long",
      "entry_date": "2026-06-02",
      "entry_price": 1750.06005859375,
      "shares": 17.400333216859043,
      "notional": 30451.62816904711,
      "sentiment": 13.618636000000002,
      "weight": 0.029221203535510387
    },
    {
      "ticker": "ADDS",
      "side": "long",
      "entry_date": "2026-06-02",
      "entry_price": 26.329999923706055,
      "shares": 1153.1760856952376,
      "notional": 30363.12624837525,
      "sentiment": 13.579056,
      "weight": 0.029136277612243508
    },
    {
      "ticker": "GME",
      "side": "short",
      "entry_date": "2026-06-02",
      "entry_price": 21.139999389648438,
      "shares": 1411.8783416452209,
      "notional": 29847.107280637818,
      "sentiment": -13.348281000000002,
      "weight": 0.02864110884160397
    },
    {
      "ticker": "MRVL",
      "side": "long",
      "entry_date": "2026-06-02",
      "entry_price": 253.4600067138672,
      "shares": 106.19413140180578,
      "notional": 26915.965258074986,
      "sentiment": 12.03741,
      "weight": 0.02582840217261024
    },
    {
      "ticker": "BOOM",
      "side": "long",
      "entry_date": "2026-06-02",
      "entry_price": 6.809999942779541,
      "shares": 3834.3993196626707,
      "notional": 26112.259147496698,
      "sentiment": 11.677975,
      "weight": 0.025057170509410916
    },
    {
      "ticker": "ASTS",
      "side": "short",
      "entry_date": "2026-06-02",
      "entry_price": 109.91000366210938,
      "shares": 237.11720417527172,
      "notional": 26061.552779253252,
      "sentiment": -11.655298,
      "weight": 0.025008512976264812
    },
    {
      "ticker": "JAN",
      "side": "short",
      "entry_date": "2026-06-02",
      "entry_price": 25.860000610351562,
      "shares": 987.1304455284253,
      "notional": 25527.193923861687,
      "sentiment": -11.416321,
      "weight": 0.02449574535715041
    },
    {
      "ticker": "HOOD",
      "side": "short",
      "entry_date": "2026-06-02",
      "entry_price": 88.66999816894531,
      "shares": 263.4018096959025,
      "notional": 23355.837983432557,
      "sentiment": -10.445242999999998,
      "weight": 0.022412124950021796
    },
    {
      "ticker": "ZM",
      "side": "long",
      "entry_date": "2026-06-02",
      "entry_price": 108.29000091552734,
      "shares": 210.84102726409648,
      "notional": 22831.975035459734,
      "sentiment": 10.21096,
      "weight": 0.021909429142019442
    },
    {
      "ticker": "TGT",
      "side": "long",
      "entry_date": "2026-06-02",
      "entry_price": 123.2300033569336,
      "shares": 181.83790640496107,
      "notional": 22407.88581670113,
      "sentiment": 10.021298,
      "weight": 0.021502475618557036
    },
    {
      "ticker": "NOW",
      "side": "long",
      "entry_date": "2026-06-02",
      "entry_price": 129.89999389648438,
      "shares": 171.68523968021802,
      "notional": 22301.911586576778,
      "sentiment": 9.973904000000001,
      "weight": 0.021400783369761932
    },
    {
      "ticker": "MSTR",
      "side": "short",
      "entry_date": "2026-06-02",
      "entry_price": 142.69000244140625,
      "shares": 151.34089807788928,
      "notional": 21594.833116218637,
      "sentiment": -9.657682999999999,
      "weight": 0.020722275022582178
    },
    {
      "ticker": "SMCI",
      "side": "long",
      "entry_date": "2026-06-02",
      "entry_price": 48.7599983215332,
      "shares": 435.9409930546838,
      "notional": 21256.4820896339,
      "sentiment": 9.506364999999999,
      "weight": 0.020397595364752545
    },
    {
      "ticker": "SNOW",
      "side": "long",
      "entry_date": "2026-06-02",
      "entry_price": 265.45001220703125,
      "shares": 75.96797266547107,
      "notional": 20165.69927139271,
      "sentiment": 9.018543,
      "weight": 0.019350886579004856
    },
    {
      "ticker": "NASA",
      "side": "short",
      "entry_date": "2026-06-02",
      "entry_price": 37.36000061035156,
      "shares": 536.516963921859,
      "notional": 20044.274099584618,
      "sentiment": -8.964239,
      "weight": 0.019234367697320058
    },
    {
      "ticker": "RSI",
      "side": "short",
      "entry_date": "2026-06-02",
      "entry_price": 25.149999618530273,
      "shares": 752.7387476930523,
      "notional": 18931.379217333222,
      "sentiment": -8.466528,
      "weight": 0.018166440304821837
    }
  ],
  "positions": {
    "long": {
      "DELL": {
        "ticker": "DELL",
        "side": "long",
        "entry_date": "2026-06-02",
        "entry_price": 466.1099853515625,
        "shares": 276.5659700702741,
        "notional": 128910.16025819612,
        "sentiment": 57.651451,
        "weight": 0.12370143263895912
      },
      "CRSR": {
        "ticker": "CRSR",
        "side": "long",
        "entry_date": "2026-06-02",
        "entry_price": 11.119999885559082,
        "shares": 6813.972891042895,
        "notional": 75771.37776859968,
        "sentiment": 33.886621999999996,
        "weight": 0.07270976906886298
      },
      "HPE": {
        "ticker": "HPE",
        "side": "long",
        "entry_date": "2026-06-02",
        "entry_price": 63.060001373291016,
        "shares": 988.3475700138507,
        "notional": 62325.19912236226,
        "sentiment": 27.873196,
        "weight": 0.05980689501512294
      },
      "RIVN": {
        "ticker": "RIVN",
        "side": "long",
        "entry_date": "2026-06-02",
        "entry_price": 16.989999771118164,
        "shares": 2183.0696127016336,
        "notional": 37090.35222013577,
        "sentiment": 16.587619,
        "weight": 0.035591684142853894
      },
      "NVDA": {
        "ticker": "NVDA",
        "side": "long",
        "entry_date": "2026-06-02",
        "entry_price": 227.17999267578125,
        "shares": 156.41749502552216,
        "notional": 35534.92537426217,
        "sentiment": 15.891998000000001,
        "weight": 0.03409910567724433
      },
      "SNDK": {
        "ticker": "SNDK",
        "side": "long",
        "entry_date": "2026-06-02",
        "entry_price": 1750.06005859375,
        "shares": 17.400333216859043,
        "notional": 30451.62816904711,
        "sentiment": 13.618636000000002,
        "weight": 0.029221203535510387
      },
      "ADDS": {
        "ticker": "ADDS",
        "side": "long",
        "entry_date": "2026-06-02",
        "entry_price": 26.329999923706055,
        "shares": 1153.1760856952376,
        "notional": 30363.12624837525,
        "sentiment": 13.579056,
        "weight": 0.029136277612243508
      },
      "MRVL": {
        "ticker": "MRVL",
        "side": "long",
        "entry_date": "2026-06-02",
        "entry_price": 253.4600067138672,
        "shares": 106.19413140180578,
        "notional": 26915.965258074986,
        "sentiment": 12.03741,
        "weight": 0.02582840217261024
      },
      "BOOM": {
        "ticker": "BOOM",
        "side": "long",
        "entry_date": "2026-06-02",
        "entry_price": 6.809999942779541,
        "shares": 3834.3993196626707,
        "notional": 26112.259147496698,
        "sentiment": 11.677975,
        "weight": 0.025057170509410916
      },
      "ZM": {
        "ticker": "ZM",
        "side": "long",
        "entry_date": "2026-06-02",
        "entry_price": 108.29000091552734,
        "shares": 210.84102726409648,
        "notional": 22831.975035459734,
        "sentiment": 10.21096,
        "weight": 0.021909429142019442
      },
      "TGT": {
        "ticker": "TGT",
        "side": "long",
        "entry_date": "2026-06-02",
        "entry_price": 123.2300033569336,
        "shares": 181.83790640496107,
        "notional": 22407.88581670113,
        "sentiment": 10.021298,
        "weight": 0.021502475618557036
      },
      "NOW": {
        "ticker": "NOW",
        "side": "long",
        "entry_date": "2026-06-02",
        "entry_price": 129.89999389648438,
        "shares": 171.68523968021802,
        "notional": 22301.911586576778,
        "sentiment": 9.973904000000001,
        "weight": 0.021400783369761932
      },
      "SMCI": {
        "ticker": "SMCI",
        "side": "long",
        "entry_date": "2026-06-02",
        "entry_price": 48.7599983215332,
        "shares": 435.9409930546838,
        "notional": 21256.4820896339,
        "sentiment": 9.506364999999999,
        "weight": 0.020397595364752545
      },
      "SNOW": {
        "ticker": "SNOW",
        "side": "long",
        "entry_date": "2026-06-02",
        "entry_price": 265.45001220703125,
        "shares": 75.96797266547107,
        "notional": 20165.69927139271,
        "sentiment": 9.018543,
        "weight": 0.019350886579004856
      }
    },
    "short": {
      "MSFT": {
        "ticker": "MSFT",
        "side": "short",
        "entry_date": "2026-06-02",
        "entry_price": 446.8800048828125,
        "shares": 265.39348645830177,
        "notional": 118599.04252435254,
        "sentiment": -53.040093000000006,
        "weight": 0.11380694462319131
      },
      "META": {
        "ticker": "META",
        "side": "short",
        "entry_date": "2026-06-02",
        "entry_price": 603.239990234375,
        "shares": 187.19685570659806,
        "notional": 112924.62940835393,
        "sentiment": -50.502371,
        "weight": 0.10836181112534742
      },
      "SPCE": {
        "ticker": "SPCE",
        "side": "short",
        "entry_date": "2026-06-02",
        "entry_price": 6.739999771118164,
        "shares": 6860.204871306986,
        "notional": 46237.7792624328,
        "sentiment": -20.678549,
        "weight": 0.044369501405869476
      },
      "GOOGL": {
        "ticker": "GOOGL",
        "side": "short",
        "entry_date": "2026-06-02",
        "entry_price": 366.5899963378906,
        "shares": 99.68814534151198,
        "notional": 36544.676835675986,
        "sentiment": -16.343581,
        "weight": 0.03506805724891247
      },
      "GME": {
        "ticker": "GME",
        "side": "short",
        "entry_date": "2026-06-02",
        "entry_price": 21.139999389648438,
        "shares": 1411.8783416452209,
        "notional": 29847.107280637818,
        "sentiment": -13.348281000000002,
        "weight": 0.02864110884160397
      },
      "ASTS": {
        "ticker": "ASTS",
        "side": "short",
        "entry_date": "2026-06-02",
        "entry_price": 109.91000366210938,
        "shares": 237.11720417527172,
        "notional": 26061.552779253252,
        "sentiment": -11.655298,
        "weight": 0.025008512976264812
      },
      "JAN": {
        "ticker": "JAN",
        "side": "short",
        "entry_date": "2026-06-02",
        "entry_price": 25.860000610351562,
        "shares": 987.1304455284253,
        "notional": 25527.193923861687,
        "sentiment": -11.416321,
        "weight": 0.02449574535715041
      },
      "HOOD": {
        "ticker": "HOOD",
        "side": "short",
        "entry_date": "2026-06-02",
        "entry_price": 88.66999816894531,
        "shares": 263.4018096959025,
        "notional": 23355.837983432557,
        "sentiment": -10.445242999999998,
        "weight": 0.022412124950021796
      },
      "MSTR": {
        "ticker": "MSTR",
        "side": "short",
        "entry_date": "2026-06-02",
        "entry_price": 142.69000244140625,
        "shares": 151.34089807788928,
        "notional": 21594.833116218637,
        "sentiment": -9.657682999999999,
        "weight": 0.020722275022582178
      },
      "NASA": {
        "ticker": "NASA",
        "side": "short",
        "entry_date": "2026-06-02",
        "entry_price": 37.36000061035156,
        "shares": 536.516963921859,
        "notional": 20044.274099584618,
        "sentiment": -8.964239,
        "weight": 0.019234367697320058
      },
      "RSI": {
        "ticker": "RSI",
        "side": "short",
        "entry_date": "2026-06-02",
        "entry_price": 25.149999618530273,
        "shares": 752.7387476930523,
        "notional": 18931.379217333222,
        "sentiment": -8.466528,
        "weight": 0.018166440304821837
      }
    }
  },
  "today_profit": 42838.11135976568,
  "total_profit": 42107.2537974515,
  "total_investment": 1042107.2537974515
}